autopartial/__init__.py
autopartial/autopartial.py
autopartial-0.0.1.dist-info/LICENSE
autopartial-0.0.1.dist-info/METADATA
autopartial-0.0.1.dist-info/WHEEL
autopartial-0.0.1.dist-info/top_level.txt
autopartial-0.0.1.dist-info/RECORD
