Metadata-Version: 2.1
Name: autopartial
Version: 0.0.1
Summary: autopartial
Author: Janith Petangoda
Requires-Python: >=3.8
License-File: LICENSE
Provides-Extra: test
Requires-Dist: pytest ; extra == 'test'
Requires-Dist: pytest-xdist ; extra == 'test'
